{"cameraMode":{"drawMode":0,"name":"Shaded","section":"Shading Mode"},"sceneLighting":true,"audioPlay":false,"sceneViewState":{"m_AlwaysRefresh":false,"showFog":true,"showSkybox":true,"showFlares":true,"showImageEffects":true,"showParticleSystems":true,"showVisualEffectGraphs":true,"m_FxEnabled":true},"in2DMode":false,"pivot":{"x":-5.648182392120361,"y":5.590923309326172,"z":5.697727203369141},"rotation":{"x":0.05217893421649933,"y":0.0,"z":0.0,"w":0.998637855052948},"size":5.8155903816223148,"orthographic":false}